main.py
setup.py
SALMONN.egg-info/PKG-INFO
SALMONN.egg-info/SOURCES.txt
SALMONN.egg-info/dependency_links.txt
SALMONN.egg-info/requires.txt
SALMONN.egg-info/top_level.txt